Quartus/VendingMachine/DisplayDecimal.vhd
library ieee;
use ieee.std_logic_1164.all;

entity DisplayDecimal is
	port(
		EN	: in std_logic;
		DIG	: in std_logic_vector(3 downto 0);
		HEX	: out std_logic_vector(6 downto 0)
	);
end entity DisplayDecimal;

architecture DisplayDecimal_ARCH of DisplayDecimal is
begin
	process(EN, DIG)
	begin
		if EN = '0' then
			HEX <= "1111111";
		else
			case DIG is
				when "0000" => HEX <= "1000000"; -- 0
				when "0001" => HEX <= "1111001"; -- 1
				when "0010" => HEX <= "0100100"; -- 2
				when "0011" => HEX <= "0110000"; -- 3
				when "0100" => HEX <= "0011001"; -- 4
				when "0101" => HEX <= "0010010"; -- 5
				when "0110" => HEX <= "0000010"; -- 6
				when "0111" => HEX <= "1111000"; -- 7
				when "1000" => HEX <= "0000000"; -- 8
				when "1001" => HEX <= "0010000"; -- 9
				when others => HEX <= "1111111"; -- Blank
			end case;
		end if;
	end process;
end architecture DisplayDecimal_ARCH;

Quartus/VendingMachine/DisplayHexadecimal.vhd
library ieee;
use ieee.std_logic_1164.all;

entity DisplayHexadecimal is
	port(
		EN	: in std_logic;
		DIG	: in std_logic_vector(3 downto 0);
		HEX	: out std_logic_vector(6 downto 0)
	);
end entity DisplayHexadecimal;

architecture DisplayHexadecimal_ARCH of DisplayHexadecimal is
begin
	process(EN, DIG)
	begin
		if EN = '0' then
			HEX <= "1111111";
		else
			case DIG is
				when "0000" => HEX <= "1000000"; -- 0
				when "0001" => HEX <= "1111001"; -- 1
				when "0010" => HEX <= "0100100"; -- 2
				when "0011" => HEX <= "0110000"; -- 3
				when "0100" => HEX <= "0011001"; -- 4
				when "0101" => HEX <= "0010010"; -- 5
				when "0110" => HEX <= "0000010"; -- 6
				when "0111" => HEX <= "1111000"; -- 7
				when "1000" => HEX <= "0000000"; -- 8
				when "1001" => HEX <= "0010000"; -- 9
				when "1010" => HEX <= "0001000"; -- A
				when "1011" => HEX <= "0000011"; -- b
				when "1100" => HEX <= "1000110"; -- C
				when "1101" => HEX <= "0100001"; -- d
				when "1110" => HEX <= "0000110"; -- E
				when others => HEX <= "0001110"; -- F
			end case;
		end if;
	end process;
end architecture DisplayHexadecimal_ARCH;

Quartus/VendingMachine/Delay.vhd
library ieee;
use ieee.std_logic_1164.all;
use ieee.numeric_std.all;

entity Delay is
	port (
		CLK		: in  std_logic;
		RST		: in  std_logic;
		START	: in  std_logic;
		DONE	: out std_logic
	);
end entity Delay;

architecture Delay_ARCH of Delay is
	constant DELAY_CYCLES	: integer := 25;
	signal counter			: integer range 0 to DELAY_CYCLES;
begin
	process(CLK, RST)
	begin
		if (RST = '1') then
			counter <= 0;
			DONE  <= '0';
		elsif (rising_edge(CLK)) then
			if (START = '1') then
				if (counter < DELAY_CYCLES - 1) then
					counter <= counter + 1;
					DONE  <= '0';
				else
					DONE <= '1';
				end if;
			else
				counter <= 0;
				DONE  <= '0';
			end if;
		end if;
	end process;
end architecture Delay_ARCH;

Quartus/VendingMachine/StateMachine.vhd
library ieee;
use ieee.std_logic_1164.all;
use work.time_system.all;
use work.vending_machine.all;

entity StateMachine is
	port(
		clk, rst, btn					: in std_logic;
		nickel_in, dime_in, quarter_in	: in std_logic;
		candy_out, nickel_out, dime_out	: out std_logic;
		present_state_out				: out state
	);
end StateMachine;

architecture StateMachine_ARCH of StateMachine is
	signal present_state	: state;
	signal next_state		: state;
    signal btn_prev			: std_logic := '0';
    signal btn_click		: std_logic := '0';
	signal delay_start		: std_logic := '0';
	signal delay_done		: std_logic := '0';
begin
	btn_click <= btn and (not btn_prev);
	delay0 : component Delay
		port map(
			CLK		=> clk,
			RST		=> '0',
			START	=> delay_start,
			DONE	=> delay_done
		);

	process (rst, clk)
	begin
		if (rst = '1') then
			present_state <= st0;
		elsif (rising_edge(clk)) then
			present_state <= next_state;
			btn_prev <= btn;
		end if;
		present_state_out <= present_state;
	end process;

	process (btn_click, delay_done, present_state)
	begin
		case present_state is
			when st0 =>
				delay_start	<= '0';
				candy_out	<= '0';
				nickel_out	<= '0';
				dime_out	<= '0';
				if (btn_click = '1' and nickel_in = '1') then
					next_state <= st5;
				elsif (btn_click = '1' and dime_in = '1') then
					next_state <= st10;
				elsif (btn_click = '1' and quarter_in = '1') then
					next_state <= st25;
				else
					next_state <= st0;
				end if;

			when st5 =>
				delay_start	<= '0';
				candy_out	<= '0';
				nickel_out	<= '0';
				dime_out	<= '0';
				if (btn_click = '1' and nickel_in = '1') then
					next_state <= st10;
				elsif (btn_click = '1' and dime_in = '1') then
					next_state <= st15;
				elsif (btn_click = '1' and quarter_in = '1') then
					next_state <= st30;
				else
					next_state <= st5;
				end if;

			when st10 =>
				delay_start	<= '0';
				candy_out	<= '0';
				nickel_out	<= '0';
				dime_out	<= '0';
				if (btn_click = '1' and nickel_in = '1') then
					next_state <= st15;
				elsif (btn_click = '1' and dime_in = '1') then
					next_state <= st20;
				elsif (btn_click = '1' and quarter_in = '1') then
					next_state <= st35;
				else
					next_state <= st10;
				end if;

			when st15 =>
				delay_start	<= '0';
				candy_out	<= '0';
				nickel_out	<= '0';
				dime_out	<= '0';
				if (btn_click = '1' and nickel_in = '1') then
					next_state <= st20;
				elsif (btn_click = '1' and dime_in = '1') then
					next_state <= st25;
				elsif (btn_click = '1' and quarter_in = '1') then
					next_state <= st40;
				else
					next_state <= st15;
				end if;

			when st20 =>
				delay_start	<= '0';
				candy_out	<= '0';
				nickel_out	<= '0';
				dime_out	<= '0';
				if (btn_click = '1' and nickel_in = '1') then
					next_state <= st25;
				elsif (btn_click = '1' and dime_in = '1') then
					next_state <= st30;
				elsif (btn_click = '1' and quarter_in = '1') then
					next_state <= st45;
				else
					next_state <= st20;
				end if;

			when st25 =>
				delay_start	<= '1';
				if (delay_done = '1') then
					candy_out	<= '1';
					nickel_out	<= '0';
					dime_out	<= '0';
					next_state	<= st0;
					delay_start	<= '0';
				else
					candy_out	<= '0';
					nickel_out	<= '0';
					dime_out	<= '0';
					next_state <= st25;
				end if;

			when st30 =>
				delay_start	<= '1';
				if (delay_done = '1') then
					candy_out	<= '1';
					nickel_out	<= '1';
					dime_out	<= '0';
					next_state	<= st0;
					delay_start	<= '0';
				else
					candy_out	<= '0';
					nickel_out	<= '0';
					dime_out	<= '0';
					next_state <= st30;
				end if;

			when st35 =>
				delay_start	<= '1';
				if (delay_done = '1') then
					candy_out	<= '1';
					nickel_out	<= '0';
					dime_out	<= '1';
					next_state	<= st0;
					delay_start	<= '0';
				else
					candy_out	<= '0';
					nickel_out	<= '0';
					dime_out	<= '0';
					next_state <= st35;
				end if;

			when st40 =>
				delay_start	<= '1';
				if (delay_done = '1') then
					candy_out	<= '0';
					nickel_out	<= '1';
					dime_out	<= '0';
					next_state	<= st35;
					delay_start	<= '0';
				else
					candy_out	<= '0';
					nickel_out	<= '0';
					dime_out	<= '0';
					next_state <= st40;
				end if;

			when st45 =>
				delay_start	<= '1';
				if (delay_done = '1') then
					candy_out	<= '0';
					nickel_out	<= '0';
					dime_out	<= '1';
					next_state	<= st35;
					delay_start	<= '0';
				else
					candy_out	<= '0';
					nickel_out	<= '0';
					dime_out	<= '0';
					next_state <= st45;
				end if;
		end case;
	end process;

end StateMachine_ARCH;

Quartus/VendingMachine/Clock.vhd
library ieee;
use ieee.std_logic_1164.all;
use ieee.numeric_std.all;

entity Clock is
	port(
		CLK_IN	: in std_logic;
		CLK_OUT	: out std_logic
	);
end entity Clock;

architecture Clock_ARCH of Clock is
	constant MAX_COUNT : unsigned(25 downto 0) := to_unsigned(99999999, 26); -- 50M - 1
	signal counter     : unsigned(25 downto 0) := (others => '0');
   signal clk_1s_reg  : STD_LOGIC := '0';
begin
	process(CLK_IN)
    begin
		if rising_edge(CLK_IN) then
			if counter = MAX_COUNT then
				counter    <= (others => '0');
				clk_1s_reg <= '1';  -- Pulso alto por 1 ciclo
			else
				counter    <= counter + 1;
				clk_1s_reg <= '0';
			end if;
		end if;
    end process;

    CLK_OUT <= clk_1s_reg;
end architecture Clock_ARCH;

Quartus/VendingMachine/VendingMachine.vhd
library ieee;
use ieee.std_logic_1164.all;
use ieee.numeric_std.all;
use work.time_system.all;
use work.vending_machine.all;
use work.display_segment.all;

entity VendingMachine is
	port(
		CLOCK_50	: in std_logic;
		SW			: in std_logic_vector(3 downto 0);
		KEY			: in std_logic_vector(1 downto 0);
		HEX0		: out std_logic_vector(6 downto 0);
		HEX1		: out std_logic_vector(6 downto 0);
		HEX2		: out std_logic_vector(6 downto 0);
		HEX3		: out std_logic_vector(6 downto 0);
		HEX4		: out std_logic_vector(6 downto 0);
		HEX5		: out std_logic_vector(6 downto 0)
	);
end VendingMachine;

architecture VendingMachine_ARCH of VendingMachine is
	signal clk										: std_logic;
	signal present_state							: state;
	signal candy_out								: std_logic;
	signal nickel_out, dime_out						: std_logic;
	signal present_state_dig0, present_state_dig1	: std_logic_vector(3 downto 0);
	signal candy_out_dig							: std_logic_vector(3 downto 0);
begin
	clock0 : component Clock
		port map(
			CLK_IN	=> CLOCK_50,
			CLK_OUT	=> clk
		);

	state_machine0 : component StateMachine
		port map(
			clk					=> clk,
			rst					=> not KEY(0),
			btn					=> not KEY(1),
			nickel_in			=> SW(0),
			dime_in				=> SW(1),
			quarter_in			=> SW(2),
			candy_out			=> candy_out,
			nickel_out			=> nickel_out,
			dime_out			=> dime_out,
			present_state_out	=> present_state
		);

	display5 : component DisplayHexadecimal
		port map(
			EN	=> '0',
			DIG	=> std_logic_vector(to_unsigned(0, 4)),
			HEX	=> HEX5
		);

	display4 : component DisplayDecimal
		port map(
			EN	=> '1',
			DIG	=> candy_out_dig,
			HEX	=> HEX4
		);

	display3 : component DisplayDecimal
		port map(
			EN	=> '1',
			DIG	=> present_state_dig1,
			HEX	=> HEX3
		);

	display2 : component DisplayDecimal
		port map(
			EN	=> '1',
			DIG	=> present_state_dig0,
			HEX	=> HEX2
		);

	display1 : component DisplayDecimal
		port map(
			EN	=> '1',
			DIG	=> "000" & dime_out,
			HEX	=> HEX1
		);

	display0 : component DisplayDecimal
		port map(
			EN	=> '1',
			DIG	=> "000" & nickel_out,
			HEX	=> HEX0
		);

	with present_state select
		present_state_dig1 <=
			std_logic_vector(to_unsigned(1, 4)) when st10,
			std_logic_vector(to_unsigned(1, 4)) when st15,
			std_logic_vector(to_unsigned(2, 4)) when st20,
			std_logic_vector(to_unsigned(2, 4)) when st25,
			std_logic_vector(to_unsigned(3, 4)) when st30,
			std_logic_vector(to_unsigned(3, 4)) when st35,
			std_logic_vector(to_unsigned(4, 4)) when st40,
			std_logic_vector(to_unsigned(4, 4)) when st45,
			std_logic_vector(to_unsigned(0, 4)) when others;
	with present_state select
		present_state_dig0 <=
			std_logic_vector(to_unsigned(5, 4)) when st5,
			std_logic_vector(to_unsigned(5, 4)) when st15,
			std_logic_vector(to_unsigned(5, 4)) when st25,
			std_logic_vector(to_unsigned(5, 4)) when st35,
			std_logic_vector(to_unsigned(5, 4)) when st45,
			std_logic_vector(to_unsigned(0, 4)) when others;
	candy_out_dig <= std_logic_vector(to_unsigned(1, 4)) when candy_out = '1' else std_logic_vector(to_unsigned(0, 4));
end VendingMachine_ARCH;

Quartus/VendingMachine/simulation/questa/VendingMachine.vht
-- Copyright (C) 2025  Altera Corporation. All rights reserved.
-- Your use of Altera Corporation's design tools, logic functions 
-- and other software and tools, and any partner logic 
-- functions, and any output files from any of the foregoing 
-- (including device programming or simulation files), and any 
-- associated documentation or information are expressly subject 
-- to the terms and conditions of the Altera Program License 
-- Subscription Agreement, the Altera Quartus Prime License Agreement,
-- the Altera IP License Agreement, or other applicable license
-- agreement, including, without limitation, that your use is for
-- the sole purpose of programming logic devices manufactured by
-- Altera and sold by Altera or its authorized distributors.  Please
-- refer to the Altera Software License Subscription Agreements 
-- on the Quartus Prime software download page.

-- ***************************************************************************
-- This file contains a Vhdl test bench template that is freely editable to   
-- suit user's needs .Comments are provided in each section to help the user  
-- fill out necessary details.                                                
-- ***************************************************************************
-- Generated on "08/09/2025 15:14:32"
                                                            
-- Vhdl Test Bench template for design  :  VendingMachine
-- 
-- Simulation tool : Questa Intel FPGA (VHDL)
-- 

LIBRARY ieee;                                               
USE ieee.std_logic_1164.all;                                

ENTITY VendingMachine_vhd_tst IS
END VendingMachine_vhd_tst;
ARCHITECTURE VendingMachine_arch OF VendingMachine_vhd_tst IS
-- constants                                            
CONSTANT CLOCK_PERIOD : TIME := 10 ns;
CONSTANT WAIT_TIME : TIME := 1000 ns;
-- signals                                                   
SIGNAL CLOCK_50 : STD_LOGIC;
SIGNAL HEX0 : STD_LOGIC_VECTOR(6 DOWNTO 0);
SIGNAL HEX1 : STD_LOGIC_VECTOR(6 DOWNTO 0);
SIGNAL HEX2 : STD_LOGIC_VECTOR(6 DOWNTO 0);
SIGNAL HEX3 : STD_LOGIC_VECTOR(6 DOWNTO 0);
SIGNAL HEX4 : STD_LOGIC_VECTOR(6 DOWNTO 0);
SIGNAL HEX5 : STD_LOGIC_VECTOR(6 DOWNTO 0);
SIGNAL KEY : STD_LOGIC_VECTOR(1 DOWNTO 0);
SIGNAL SW : STD_LOGIC_VECTOR(3 DOWNTO 0);
COMPONENT VendingMachine
	PORT (
	CLOCK_50 : IN STD_LOGIC;
	HEX0 : OUT STD_LOGIC_VECTOR(6 DOWNTO 0);
	HEX1 : OUT STD_LOGIC_VECTOR(6 DOWNTO 0);
	HEX2 : OUT STD_LOGIC_VECTOR(6 DOWNTO 0);
	HEX3 : OUT STD_LOGIC_VECTOR(6 DOWNTO 0);
	HEX4 : OUT STD_LOGIC_VECTOR(6 DOWNTO 0);
	HEX5 : OUT STD_LOGIC_VECTOR(6 DOWNTO 0);
	KEY : IN STD_LOGIC_VECTOR(1 DOWNTO 0);
	SW : IN STD_LOGIC_VECTOR(3 DOWNTO 0)
	);
END COMPONENT;
BEGIN
	i1 : VendingMachine
	PORT MAP (
-- list connections between master ports and signals
	CLOCK_50 => CLOCK_50,
	HEX0 => HEX0,
	HEX1 => HEX1,
	HEX2 => HEX2,
	HEX3 => HEX3,
	HEX4 => HEX4,
	HEX5 => HEX5,
	KEY => KEY,
	SW => SW
	);
	
	clk_process : PROCESS
	BEGIN
		 LOOP
			  CLOCK_50 <= '0';
			  WAIT FOR CLOCK_PERIOD / 2;
			  CLOCK_50 <= '1';
			  WAIT FOR CLOCK_PERIOD / 2;
		 END LOOP;
	END PROCESS;
	
init : PROCESS                                               
-- variable declarations
	PROCEDURE insert_coin(nickel, dime, quarter : BOOLEAN) IS
	BEGIN
		IF nickel THEN
			SW <= "0001";
		ELSIF dime THEN
			SW <= "0010";
		ELSIF quarter THEN
			SW <= "0100";
		ELSE
			SW <= "0000";
		END IF;
	END PROCEDURE;
	
	PROCEDURE press_btn IS
	BEGIN
		KEY(1) <= '0';
		WAIT FOR 100 ns;
		KEY(1) <= '1';
		WAIT FOR 100 ns;
	END PROCEDURE;
BEGIN
	KEY <= (OTHERS => '1');
	SW <= (OTHERS => '0');
	
	-- resetar
	KEY(0) <= '0';
	WAIT FOR 100 ns;
	KEY(0) <= '1';
	WAIT FOR 100 ns;
	
	-- 5 nickels (troco 0)
	insert_coin(TRUE, FALSE, FALSE);
	press_btn;
	insert_coin(TRUE, FALSE, FALSE);
	press_btn;
	insert_coin(TRUE, FALSE, FALSE);
	press_btn;
	insert_coin(TRUE, FALSE, FALSE);
	press_btn;
	insert_coin(TRUE, FALSE, FALSE);
	press_btn;
	WAIT FOR WAIT_TIME;
	
	-- 3 nickels + 1 dime (troco 0)
	insert_coin(TRUE, FALSE, FALSE);
	press_btn;
	insert_coin(TRUE, FALSE, FALSE);
	press_btn;
	insert_coin(TRUE, FALSE, FALSE);
	press_btn;
	insert_coin(FALSE, TRUE, FALSE);
	press_btn;
	WAIT FOR WAIT_TIME;
	
	-- 3 dimes (troco nickel)
	insert_coin(FALSE, TRUE, FALSE);
	press_btn;
	insert_coin(FALSE, TRUE, FALSE);
	press_btn;
	insert_coin(FALSE, TRUE, FALSE);
	press_btn;
	WAIT FOR WAIT_TIME;
	
	-- 2 dimes + 1 nickel (troco 0)
	insert_coin(FALSE, TRUE, FALSE);
	press_btn;
	insert_coin(FALSE, TRUE, FALSE);
	press_btn;
	insert_coin(TRUE, FALSE, FALSE);
	press_btn;
	WAIT FOR WAIT_TIME;
	
	-- 1 dime + 1 quarter (troco dime)
	insert_coin(FALSE, TRUE, FALSE);
	press_btn;
	insert_coin(FALSE, FALSE, TRUE);
	press_btn;
	WAIT FOR WAIT_TIME;
	
	-- 2 dimes + 1 quarter (troco dime + dime)
	insert_coin(FALSE, TRUE, FALSE);
	press_btn;
	insert_coin(FALSE, TRUE, FALSE);
	press_btn;
	insert_coin(FALSE, FALSE, TRUE);
	press_btn;
	WAIT FOR WAIT_TIME;
	
	-- 3 nickels + 1 quarter (troco nickel + dime)
	insert_coin(TRUE, FALSE, FALSE);
	press_btn;
	insert_coin(TRUE, FALSE, FALSE);
	press_btn;
	insert_coin(TRUE, FALSE, FALSE);
	press_btn;
	insert_coin(FALSE, FALSE, TRUE);
	press_btn;
	WAIT FOR WAIT_TIME;
	
	-- 4 nickels + 1 dime (troco nickel)
	insert_coin(TRUE, FALSE, FALSE);
	press_btn;
	insert_coin(TRUE, FALSE, FALSE);
	press_btn;
	insert_coin(TRUE, FALSE, FALSE);
	press_btn;
	insert_coin(TRUE, FALSE, FALSE);
	press_btn;
	insert_coin(FALSE, TRUE, FALSE);
	press_btn;
	WAIT FOR WAIT_TIME;
	
	-- 4 nickels + 1 quarter (troco dime + dime)
	insert_coin(TRUE, FALSE, FALSE);
	press_btn;
	insert_coin(TRUE, FALSE, FALSE);
	press_btn;
	insert_coin(TRUE, FALSE, FALSE);
	press_btn;
	insert_coin(TRUE, FALSE, FALSE);
	press_btn;
	insert_coin(FALSE, FALSE, TRUE);
	press_btn;
	WAIT FOR WAIT_TIME;
	
	WAIT;
END PROCESS init;                                           
always : PROCESS                                              
-- optional sensitivity list                                  
-- (        )                                                 
-- variable declarations                                      
BEGIN                                                         
        -- code executes for every event on sensitivity list  
WAIT;                                                        
END PROCESS always;                                          
END VendingMachine_arch;

Quartus/VendingMachine/simulation/questa/teste.vcd
$date
	Sat Aug  9 18:00:10 2025
$end
$version
	Questa Intel Starter FPGA Edition Version 2024.3
$end
$timescale
	1ns
$end
$scope module vendingmachine_vhd_tst $end
$var wire 1 ! KEY [1] $end
$var wire 1 " KEY [0] $end
$var wire 1 # SW [3] $end
$var wire 1 $ SW [2] $end
$var wire 1 % SW [1] $end
$var wire 1 & SW [0] $end
$scope module i1 $end
$var wire 1 ' clk $end
$var wire 1 ) candy_out $end
$var wire 1 * nickel_out $end
$var wire 1 + dime_out $end
$upscope $end
$upscope $end
$enddefinitions $end
#0
0'
0)
0*
0+
1!
0"
0#
0$
0%
0&
0'
0+
0*
0)
0#
0$
0%
0&
1!
0"
#5
1'
#15
0'
#25
1'
#35
0'
#45
1'
#55
0'
#65
1'
#75
0'
#85
1'
#95
0'
#100
1"
#105
1'
#115
0'
#125
1'
#135
0'
#145
1'
#155
0'
#165
1'
#175
0'
#185
1'
#195
0'
#200
0!
1&
#205
1'
#215
0'
#225
1'
#235
0'
#245
1'
#255
0'
#265
1'
#275
0'
#285
1'
#295
0'
#300
1!
#305
1'
#315
0'
#325
1'
#335
0'
#345
1'
#355
0'
#365
1'
#375
0'
#385
1'
#395
0'
#400
0!
#405
1'
#415
0'
#425
1'
#435
0'
#445
1'
#455
0'
#465
1'
#475
0'
#485
1'
#495
0'
#500
1!
#505
1'
#515
0'
#525
1'
#535
0'
#545
1'
#555
0'
#565
1'
#575
0'
#585
1'
#595
0'
#600
0!
#605
1'
#615
0'
#625
1'
#635
0'
#645
1'
#655
0'
#665
1'
#675
0'
#685
1'
#695
0'
#700
1!
#705
1'
#715
0'
#725
1'
#735
0'
#745
1'
#755
0'
#765
1'
#775
0'
#785
1'
#795
0'
#800
0!
#805
1'
#815
0'
#825
1'
#835
0'
#845
1'
#855
0'
#865
1'
#875
0'
#885
1'
#895
0'
#900
1!
#905
1'
#915
0'
#925
1'
#935
0'
#945
1'
#955
0'
#965
1'
#975
0'
#985
1'
#995
0'
#1000
0!
#1005
1'
#1015
0'
#1025
1'
#1035
0'
#1045
1'
#1055
0'
#1065
1'
#1075
0'
#1085
1'
#1095
0'
#1100
1!
#1105
1'
#1115
0'
#1125
1'
#1135
0'
#1145
1'
#1155
0'
#1165
1'
#1175
0'
#1185
1'
#1195
0'
#1205
1'
#1215
0'
#1225
1'
#1235
0'
#1245
1'
#1255
0'
#1265
1'
#1275
0'
#1285
1'
#1295
0'
#1305
1'
#1315
0'
#1325
1'
#1335
0'
#1345
1'
#1355
0'
#1365
1'
#1375
0'
#1385
1'
#1395
0'
#1405
1'
#1415
0'
#1425
1'
#1435
0'
#1445
1'
#1455
0'
#1465
1'
#1475
0'
#1485
1'
#1495
0'
#1505
1'
1)
#1515
0'
#1525
1'
0)
